git_smartmv/__init__.py
git_smartmv-1.0.2.dist-info/LICENSE
git_smartmv-1.0.2.dist-info/METADATA
git_smartmv-1.0.2.dist-info/WHEEL
git_smartmv-1.0.2.dist-info/entry_points.txt
git_smartmv-1.0.2.dist-info/top_level.txt
git_smartmv-1.0.2.dist-info/RECORD
