Metadata-Version: 2.1
Name: git-smartmv
Version: 1.0.2
Summary: A command-line tool that can decide whether to use `git mv` or `mv`.
Home-page: https://github.com/jamescherti/git-smartmv
Author: James Cherti
Classifier: Development Status :: 5 - Production/Stable
Classifier: License :: OSI Approved :: GNU General Public License (GPL)
Classifier: License :: OSI Approved :: GNU General Public License v3 (GPLv3)
Classifier: Environment :: Console
Classifier: Operating System :: POSIX :: Linux
Classifier: Operating System :: POSIX :: Other
Classifier: Topic :: Text Editors :: Emacs
Classifier: Programming Language :: Python :: 3 :: Only
Classifier: Programming Language :: Python :: 3
Requires-Python: >=3.6, <4
License-File: LICENSE
